{
    "Barnard's Star": {
        "planets": {
            "Frost": {
                "link": "https://game8.co/games/Starfield/archives/425357",
                "resources": [
                    "",
                    "",
                    "",
                    ""
                ]
            }
        }
    },
    "Maheo": {
        "planets": {
            "": {
                "link": "https://game8.co/games/Starfield/archives/426570",
                "resources": [
                    "Flora",
                    "Fauna",
                    "Resources",
                    "Planet Traits"
                ]
            }
        }
    },
    "Cheyenne": {
        "planets": {
            "Skink": {
                "link": "https://game8.co/games/Starfield/archives/424071",
                "resources": [
                    "",
                    "",
                    "",
                    ""
                ]
            },
            "Washakie": {
                "link": "https://game8.co/games/Starfield/archives/424072",
                "resources": [
                    "",
                    "",
                    "",
                    ""
                ]
            },
            "Grizzit": {
                "link": "https://game8.co/games/Starfield/archives/424088",
                "resources": []
            },
            "Agamon A": {
                "link": "https://game8.co/games/Starfield/archives/424080",
                "resources": [
                    "",
                    "",
                    "",
                    ""
                ]
            },
            "Thren": {
                "link": "https://game8.co/games/Starfield/archives/424101",
                "resources": [
                    "Flora",
                    "Fauna",
                    "Resources",
                    "Planet Traits"
                ]
            },
            "Stellis": {
                "link": "https://game8.co/games/Starfield/archives/424095",
                "resources": [
                    "",
                    "",
                    "",
                    ""
                ]
            },
            "Stellis D": {
                "link": "https://game8.co/games/Starfield/archives/424099",
                "resources": [
                    "Flora",
                    "Fauna",
                    "Resources",
                    "Planet Traits"
                ]
            },
            "Navaha": {
                "link": "https://game8.co/games/Starfield/archives/424075",
                "resources": [
                    "Flora",
                    "Fauna",
                    "Resources",
                    "Planet Traits"
                ]
            },
            "Laramie": {
                "link": "https://game8.co/games/Starfield/archives/424092",
                "resources": [
                    "Flora",
                    "Fauna",
                    "Resources",
                    "Planet Traits"
                ]
            }
        }
    },
    "Alpha Centauri": {
        "planets": {
            "": {
                "link": "https://game8.co/games/Starfield/archives/423451",
                "resources": [
                    "Flora",
                    "Fauna",
                    "Resources",
                    "Planet Traits"
                ]
            }
        }
    },
    "Sol": {
        "planets": {
            "": {
                "link": "https://game8.co/games/Starfield/archives/423674",
                "resources": [
                    "Flora",
                    "Fauna",
                    "Resources",
                    "Planet Traits"
                ]
            }
        }
    },
    "Narion": {
        "planets": {
            "": {
                "link": "https://game8.co/games/Starfield/archives/423398",
                "resources": [
                    "Flora",
                    "Fauna",
                    "Resources",
                    "Planet Traits"
                ]
            }
        }
    },
    "Procyon B": {
        "planets": {
            "": {
                "link": "https://game8.co/games/Starfield/archives/428042",
                "resources": [
                    "Flora",
                    "Fauna",
                    "Resources",
                    "Planet Traits"
                ]
            }
        }
    },
    "Toliman": {
        "planets": {
            "": {
                "link": "https://game8.co/games/Starfield/archives/428019",
                "resources": [
                    "Flora",
                    "Fauna",
                    "Resources",
                    "Planet Traits"
                ]
            }
        }
    },
    "Wolf": {
        "planets": {
            "": {
                "link": "https://game8.co/games/Starfield/archives/423892",
                "resources": [
                    "Flora",
                    "Fauna",
                    "Resources",
                    "Planet Traits"
                ]
            }
        }
    },
    "Valo": {
        "planets": {
            "": {
                "link": "https://game8.co/games/Starfield/archives/423735",
                "resources": [
                    "Flora",
                    "Fauna",
                    "Resources",
                    "Planet Traits"
                ]
            }
        }
    },
    "Sirius": {
        "planets": {
            "Sirius I": {
                "link": "https://game8.co/games/Starfield/archives/428036",
                "resources": [
                    "",
                    "",
                    "",
                    ""
                ]
            },
            "Sirius III-a": {
                "link": "https://game8.co/games/Starfield/archives/428039",
                "resources": [
                    "Flora",
                    "Fauna",
                    "Resources",
                    "Planet Traits"
                ]
            }
        }
    },
    "Luyten's Star": {
        "planets": {
            "Luyten's Rock": {
                "link": "https://game8.co/games/Starfield/archives/425366",
                "resources": [
                    "Flora",
                    "Fauna",
                    "Resources",
                    "Planet Traits"
                ]
            }
        }
    },
    "Volii": {
        "planets": {
            "": {
                "link": "https://game8.co/games/Starfield/archives/424370",
                "resources": [
                    "Flora",
                    "Fauna",
                    "Resources",
                    "Planet Traits"
                ]
            }
        }
    },
    "Bessel": {
        "planets": {
            "Bessel I": {
                "link": "https://game8.co/games/Starfield/archives/426959",
                "resources": [
                    "",
                    "",
                    "",
                    ""
                ]
            },
            "Bessel III-b": {
                "link": "https://game8.co/games/Starfield/archives/426958",
                "resources": [
                    "Flora",
                    "Fauna",
                    "Resources",
                    "Planet Traits"
                ]
            }
        }
    },
    "The Pup": {
        "planets": {
            "Pup I": {
                "link": "https://game8.co/games/Starfield/archives/428116",
                "resources": [
                    "",
                    "",
                    "",
                    ""
                ]
            }
        }
    },
    "Van Maanen's Star": {
        "planets": {
            "": {
                "link": "https://game8.co/games/Starfield/archives/428156",
                "resources": [
                    "Flora",
                    "Fauna",
                    "Resources",
                    "Planet Traits"
                ]
            }
        }
    },
    "Piazzi": {
        "planets": {
            "": {
                "link": "https://game8.co/games/Starfield/archives/426848",
                "resources": [
                    "",
                    "",
                    "",
                    ""
                ]
            }
        }
    },
    "Kapteyn's Star": {
        "planets": {
            "": {
                "link": "https://game8.co/games/Starfield/archives/428047",
                "resources": [
                    "Flora",
                    "Fauna",
                    "Resources",
                    "Planet Traits"
                ]
            }
        }
    },
    "Procyon A": {
        "planets": {
            "": {
                "link": "https://game8.co/games/Starfield/archives/424030",
                "resources": [
                    "Flora",
                    "Fauna",
                    "Resources",
                    "Planet Traits"
                ]
            }
        }
    },
    "Tau Ceti": {
        "planets": {
            "": {
                "link": "https://game8.co/games/Starfield/archives/424898",
                "resources": [
                    "",
                    "",
                    "",
                    ""
                ]
            }
        }
    },
    "Olympus": {
        "planets": {
            "Nesoi": {
                "link": "https://game8.co/games/Starfield/archives/424108",
                "resources": [
                    "",
                    "",
                    "",
                    ""
                ]
            },
            "Thalassa": {
                "link": "https://game8.co/games/Starfield/archives/424623",
                "resources": [
                    "",
                    "",
                    "",
                    ""
                ]
            },
            "Aion": {
                "link": "https://game8.co/games/Starfield/archives/424627",
                "resources": [
                    "Flora",
                    "Fauna",
                    "Resources",
                    "Planet Traits"
                ]
            },
            "Mithras": {
                "link": "https://game8.co/games/Starfield/archives/424647",
                "resources": [
                    "Flora",
                    "Fauna",
                    "Resources",
                    "Planet Traits"
                ]
            }
        }
    },
    "Altair": {
        "planets": {
            "": {
                "link": "https://game8.co/games/Starfield/archives/426768",
                "resources": [
                    "",
                    "",
                    "",
                    ""
                ]
            }
        }
    },
    "Muphrid": {
        "planets": {
            "Muphrid I": {
                "link": "https://game8.co/games/Starfield/archives/4269122",
                "resources": []
            },
            "Muphrid II-a": {
                "link": "https://game8.co/games/Starfield/archives/426917",
                "resources": [
                    "Flora",
                    "Fauna",
                    "Resources",
                    "Planet Traits"
                ]
            },
            "Muphrid III-c": {
                "link": "https://game8.co/games/Starfield/archives/426921",
                "resources": [
                    "",
                    "",
                    "",
                    ""
                ]
            },
            "Muphrid V-b": {
                "link": "https://game8.co/games/Starfield/archives/426927",
                "resources": [
                    "Flora",
                    "Fauna",
                    "Resources",
                    "Planet Traits"
                ]
            },
            "Muphrid VI-a": {
                "link": "https://game8.co/games/Starfield/archives/426932",
                "resources": [
                    "Flora",
                    "Fauna",
                    "Resources",
                    "Planet Traits"
                ]
            },
            "Muphrid VII": {
                "link": "https://game8.co/games/Starfield/archives/426936",
                "resources": [
                    "Flora",
                    "Fauna",
                    "Resources",
                    "Planet Traits"
                ]
            },
            "Muphrid VIII": {
                "link": "https://game8.co/games/Starfield/archives/426940",
                "resources": [
                    "Flora",
                    "Fauna",
                    "Resources",
                    "Planet Traits"
                ]
            },
            "Muphrid VIII-d": {
                "link": "https://game8.co/games/Starfield/archives/426944",
                "resources": [
                    "Flora",
                    "Fauna",
                    "Resources",
                    "Planet Traits"
                ]
            }
        }
    },
    "Sakharov": {
        "planets": {
            "Bonner": {
                "link": "https://game8.co/games/Starfield/archives/428157",
                "resources": [
                    "Flora",
                    "Fauna",
                    "Resources",
                    "Planet Traits"
                ]
            }
        }
    },
    "Sagan": {
        "planets": {
            "": {
                "link": "https://game8.co/games/Starfield/archives/428219",
                "resources": [
                    "Flora",
                    "Fauna",
                    "Resources",
                    "Planet Traits"
                ]
            }
        }
    },
    "Andromas": {
        "planets": {
            "Andromas I": {
                "link": "https://game8.co/games/Starfield/archives/428240",
                "resources": [
                    "Flora",
                    "Fauna",
                    "Resources",
                    "Planet Traits"
                ]
            },
            "Andromas IV-a": {
                "link": "https://game8.co/games/Starfield/archives/428247",
                "resources": [
                    "Flora",
                    "Fauna",
                    "Resources",
                    "Planet Traits"
                ]
            },
            "Andromas VI": {
                "link": "https://game8.co/games/Starfield/archives/428253",
                "resources": [
                    "Flora",
                    "Fauna",
                    "Resources",
                    "Planet Traits"
                ]
            }
        }
    },
    "Arcturus": {
        "planets": {
            "": {
                "link": "https://game8.co/games/Starfield/archives/425317",
                "resources": [
                    "Flora",
                    "Fauna",
                    "Resources",
                    "Planet Traits"
                ]
            }
        }
    },
    "Aranae": {
        "planets": {
            "": {
                "link": "https://game8.co/games/Starfield/archives/426741",
                "resources": [
                    "",
                    "",
                    "",
                    ""
                ]
            }
        }
    },
    "Indum": {
        "planets": {
            "": {
                "link": "https://game8.co/games/Starfield/archives/426677",
                "resources": [
                    "Flora",
                    "Fauna",
                    "Resources",
                    "Planet Traits"
                ]
            }
        }
    },
    "Oborum Prime": {
        "planets": {
            "": {
                "link": "https://game8.co/games/Starfield/archives/426459",
                "resources": [
                    "Flora",
                    "Fauna",
                    "Resources",
                    "Planet Traits"
                ]
            }
        }
    },
    "Eridani": {
        "planets": {
            "": {
                "link": "https://game8.co/games/Starfield/archives/426653",
                "resources": [
                    "",
                    "",
                    "",
                    ""
                ]
            }
        }
    },
    "Carinae": {
        "planets": {
            "Carinae I": {
                "link": "https://game8.co/games/Starfield/archives/425286",
                "resources": [
                    "Flora",
                    "Fauna",
                    "Resources",
                    "Planet Traits"
                ]
            },
            "Carinae III-a": {
                "link": "https://game8.co/games/Starfield/archives/425290",
                "resources": [
                    "Flora",
                    "Fauna",
                    "Resources",
                    "Planet Traits"
                ]
            },
            "Carinae IV": {
                "link": "https://game8.co/games/Starfield/archives/425294",
                "resources": [
                    "Flora",
                    "Fauna",
                    "Resources",
                    "Planet Traits"
                ]
            },
            "Carinae V-b": {
                "link": "https://game8.co/games/Starfield/archives/425298",
                "resources": [
                    "Flora",
                    "Fauna",
                    "Resources",
                    "Planet Traits"
                ]
            }
        }
    },
    "Beta Andraste": {
        "planets": {
            "Beta Andraste I": {
                "link": "https://game8.co/games/Starfield/archives/428349",
                "resources": [
                    "Flora",
                    "Fauna",
                    "Resources",
                    "Planet Traits"
                ]
            },
            "Beta Andraste I-d": {
                "link": "https://game8.co/games/Starfield/archives/428389",
                "resources": [
                    "",
                    "",
                    "",
                    ""
                ]
            }
        }
    },
    "Ursae Minoris": {
        "planets": {
            "": {
                "link": "https://game8.co/games/Starfield/archives/428601",
                "resources": [
                    "Flora",
                    "Fauna",
                    "Resources",
                    "Planet Traits"
                ]
            }
        }
    },
    "Eta Cassiopeia": {
        "planets": {
            "": {
                "link": "https://game8.co/games/Starfield/archives/426506",
                "resources": [
                    "",
                    "",
                    "",
                    ""
                ]
            }
        }
    },
    "McClure": {
        "planets": {
            "": {
                "link": "https://game8.co/games/Starfield/archives/428402",
                "resources": [
                    "Flora",
                    "Fauna",
                    "Resources",
                    "Planet Traits"
                ]
            }
        }
    },
    "Bradbury": {
        "planets": {
            "": {
                "link": "https://game8.co/games/Starfield/archives/428421",
                "resources": [
                    "Flora",
                    "Fauna",
                    "Resources",
                    "Planet Traits"
                ]
            }
        }
    },
    "Guniibuu": {
        "planets": {
            "": {
                "link": "https://game8.co/games/Starfield/archives/427682",
                "resources": [
                    "Flora",
                    "Fauna",
                    "Resources",
                    "Planet Traits"
                ]
            }
        }
    },
    "Kryx": {
        "planets": {
            "": {
                "link": "https://game8.co/games/Starfield/archives/426164",
                "resources": [
                    "Flora",
                    "Fauna",
                    "Resources",
                    "Planet Traits"
                ]
            }
        }
    },
    "Delta Pavonis": {
        "planets": {
            "Curie": {
                "link": "https://game8.co/games/Starfield/archives/426720",
                "resources": [
                    "Flora",
                    "Fauna",
                    "Resources",
                    "Planet Traits"
                ]
            },
            "Bitsy": {
                "link": "https://game8.co/games/Starfield/archives/426724",
                "resources": [
                    "",
                    "",
                    "",
                    ""
                ]
            },
            "Nascent": {
                "link": "https://game8.co/games/Starfield/archives/426728",
                "resources": [
                    "Flora",
                    "Fauna",
                    "Resources",
                    "Planet Traits"
                ]
            },
            "Herald": {
                "link": "https://game8.co/games/Starfield/archives/426733",
                "resources": [
                    "",
                    "",
                    "",
                    ""
                ]
            },
            "Ampere": {
                "link": "https://game8.co/games/Starfield/archives/426717",
                "resources": [
                    "Flora",
                    "Fauna",
                    "Resources",
                    "Planet Traits"
                ]
            }
        }
    },
    "Vega": {
        "planets": {
            "": {
                "link": "https://game8.co/games/Starfield/archives/428460",
                "resources": [
                    "",
                    "",
                    "",
                    ""
                ]
            }
        }
    },
    "Kumasi": {
        "planets": {
            "": {
                "link": "https://game8.co/games/Starfield/archives/426575",
                "resources": [
                    "Flora",
                    "Fauna",
                    "Resources",
                    "Planet Traits"
                ]
            }
        }
    },
    "Groombridge": {
        "planets": {
            "": {
                "link": "https://game8.co/games/Starfield/archives/427976",
                "resources": [
                    "Flora",
                    "Fauna",
                    "Resources",
                    "Planet Traits"
                ]
            }
        }
    },
    "Oborum Proxima": {
        "planets": {
            "": {
                "link": "https://game8.co/games/Starfield/archives/425336",
                "resources": [
                    "Flora",
                    "Fauna",
                    "Resources",
                    "Planet Traits"
                ]
            }
        }
    },
    "Lunara": {
        "planets": {
            "Numitor": {
                "link": "https://game8.co/games/Starfield/archives/428578",
                "resources": [
                    "Flora",
                    "Fauna",
                    "Resources",
                    "Planet Traits"
                ]
            },
            "Vesta Lunaris": {
                "link": "https://game8.co/games/Starfield/archives/428583",
                "resources": [
                    "Flora",
                    "Fauna",
                    "Resources",
                    "Planet Traits"
                ]
            },
            "Coeus": {
                "link": "https://game8.co/games/Starfield/archives/428587",
                "resources": [
                    "Flora",
                    "Fauna",
                    "Resources",
                    "Planet Traits"
                ]
            },
            "Gasparis": {
                "link": "https://game8.co/games/Starfield/archives/428592",
                "resources": [
                    "",
                    "",
                    "",
                    ""
                ]
            },
            "Okoro Beta": {
                "link": "https://game8.co/games/Starfield/archives/428598",
                "resources": [
                    "Flora",
                    "Fauna",
                    "Resources",
                    "Planet Traits"
                ]
            },
            "Cthol": {
                "link": "https://game8.co/games/Starfield/archives/428604",
                "resources": [
                    "Flora",
                    "Fauna",
                    "Resources",
                    "Planet Traits"
                ]
            },
            "Reva's World": {
                "link": "https://game8.co/games/Starfield/archives/428609",
                "resources": [
                    "Flora",
                    "Fauna",
                    "Resources",
                    "Planet Traits"
                ]
            }
        }
    },
    "Alpha Andraste": {
        "planets": {
            "": {
                "link": "https://game8.co/games/Starfield/archives/427260",
                "resources": [
                    "",
                    "",
                    "",
                    ""
                ]
            }
        }
    },
    "Ursae Majoris": {
        "planets": {
            "": {
                "link": "https://game8.co/games/Starfield/archives/425759",
                "resources": [
                    "Flora",
                    "Fauna",
                    "Resources",
                    "Planet Traits"
                ]
            }
        }
    },
    "Copernicus": {
        "planets": {
            "": {
                "link": "https://game8.co/games/Starfield/archives/428912",
                "resources": [
                    "Flora",
                    "Fauna",
                    "Resources",
                    "Planet Traits"
                ]
            }
        }
    },
    "Copernicus Minor": {
        "planets": {
            "": {
                "link": "https://game8.co/games/Starfield/archives/428916",
                "resources": [
                    "Flora",
                    "Fauna",
                    "Resources",
                    "Planet Traits"
                ]
            }
        }
    },
    "Lantana": {
        "planets": {
            "": {
                "link": "https://game8.co/games/Starfield/archives/428371",
                "resources": [
                    "Flora",
                    "Fauna",
                    "Resources",
                    "Planet Traits"
                ]
            }
        }
    },
    "Denebola": {
        "planets": {
            "Denebola I": {
                "link": "https://game8.co/games/Starfield/archives/426466",
                "resources": [
                    "",
                    "",
                    "",
                    ""
                ]
            },
            "Denebola II-a": {
                "link": "https://game8.co/games/Starfield/archives/426469",
                "resources": [
                    "Flora",
                    "Fauna",
                    "Resources",
                    "Planet Traits"
                ]
            }
        }
    },
    "Porrima": {
        "planets": {
            "": {
                "link": "https://game8.co/games/Starfield/archives/424677",
                "resources": []
            }
        }
    },
    "Al-Battani": {
        "planets": {
            "Al-Battani I": {
                "link": "https://game8.co/games/Starfield/archives/428745",
                "resources": [
                    "Flora",
                    "Fauna",
                    "Resources",
                    "Planet Traits"
                ]
            },
            "Al-Battani II": {
                "link": "https://game8.co/games/Starfield/archives/428746",
                "resources": [
                    "Flora",
                    "Fauna",
                    "Resources",
                    "Planet Traits"
                ]
            },
            "Al-Battani IV": {
                "link": "https://game8.co/games/Starfield/archives/428753",
                "resources": [
                    "Flora",
                    "Fauna",
                    "Resources",
                    "Planet Traits"
                ]
            },
            "Al-Battani V-a": {
                "link": "https://game8.co/games/Starfield/archives/428757",
                "resources": [
                    "Flora",
                    "Fauna",
                    "Resources",
                    "Planet Traits"
                ]
            },
            "Al-Battani VII": {
                "link": "https://game8.co/games/Starfield/archives/428761",
                "resources": [
                    "",
                    "",
                    "",
                    ""
                ]
            }
        }
    },
    "Shoza": {
        "planets": {
            "": {
                "link": "https://game8.co/games/Starfield/archives/427037",
                "resources": [
                    "",
                    "",
                    "",
                    ""
                ]
            }
        }
    },
    "Alpha Tirna": {
        "planets": {
            "": {
                "link": "https://game8.co/games/Starfield/archives/428720",
                "resources": [
                    "Flora",
                    "Fauna",
                    "Resources",
                    "Planet Traits"
                ]
            }
        }
    },
    "Nemeria": {
        "planets": {
            "Nemeria I": {
                "link": "https://game8.co/games/Starfield/archives/427610",
                "resources": [
                    "Flora",
                    "Fauna",
                    "Resources",
                    "Planet Traits"
                ]
            },
            "Nemeria III": {
                "link": "https://game8.co/games/Starfield/archives/427614",
                "resources": [
                    "Flora",
                    "Fauna",
                    "Resources",
                    "Planet Traits"
                ]
            },
            "Nemeria IV-b": {
                "link": "https://game8.co/games/Starfield/archives/427619",
                "resources": [
                    "",
                    "",
                    "",
                    ""
                ]
            },
            "Nemeria V-c": {
                "link": "https://game8.co/games/Starfield/archives/427629",
                "resources": [
                    "Flora",
                    "Fauna",
                    "Resources",
                    "Planet Traits"
                ]
            },
            "Nemeria VI-c": {
                "link": "https://game8.co/games/Starfield/archives/427633",
                "resources": [
                    "Flora",
                    "Fauna",
                    "Resources",
                    "Planet Traits"
                ]
            }
        }
    },
    "Bolivar": {
        "planets": {
            "Bolivar I": {
                "link": "https://game8.co/games/Starfield/archives/428768",
                "resources": [
                    "",
                    "",
                    "",
                    ""
                ]
            }
        }
    },
    "Rivera": {
        "planets": {
            "": {
                "link": "https://game8.co/games/Starfield/archives/428803",
                "resources": [
                    "Flora",
                    "Fauna",
                    "Resources",
                    "Planet Traits"
                ]
            }
        }
    },
    "Jaffa": {
        "planets": {
            "Jaffa I": {
                "link": "https://game8.co/games/Starfield/archives/427192",
                "resources": [
                    "Flora",
                    "Fauna",
                    "Resources",
                    "Planet Traits"
                ]
            },
            "Jaffa III": {
                "link": "https://game8.co/games/Starfield/archives/427211",
                "resources": [
                    "Flora",
                    "Fauna",
                    "Resources",
                    "Planet Traits"
                ]
            },
            "Jaffa V-a": {
                "link": "https://game8.co/games/Starfield/archives/427197",
                "resources": [
                    "Flora",
                    "Fauna",
                    "Resources",
                    "Planet Traits"
                ]
            },
            "Jaffa VI-c": {
                "link": "https://game8.co/games/Starfield/archives/427201",
                "resources": [
                    "Flora",
                    "Fauna",
                    "Resources",
                    "Planet Traits"
                ]
            },
            "Jaffa VII-c": {
                "link": "https://game8.co/games/Starfield/archives/427205",
                "resources": [
                    "Flora",
                    "Fauna",
                    "Resources",
                    "Planet Traits"
                ]
            }
        }
    },
    "Nikola": {
        "planets": {
            "Nikola I": {
                "link": "https://game8.co/games/Starfield/archives/428615",
                "resources": [
                    "Flora",
                    "Fauna",
                    "Resources",
                    "Planet Traits"
                ]
            },
            "Nikola II-a": {
                "link": "https://game8.co/games/Starfield/archives/428617",
                "resources": [
                    "Flora",
                    "Fauna",
                    "Resources",
                    "Planet Traits"
                ]
            },
            "Nikola IV": {
                "link": "https://game8.co/games/Starfield/archives/428621",
                "resources": [
                    "",
                    "",
                    "",
                    ""
                ]
            },
            "Nikola VI-b": {
                "link": "https://game8.co/games/Starfield/archives/428625",
                "resources": [
                    "Flora",
                    "Fauna",
                    "Resources",
                    "Planet Traits"
                ]
            },
            "Nikola VIII": {
                "link": "https://game8.co/games/Starfield/archives/428628",
                "resources": [
                    "Flora",
                    "Fauna",
                    "Resources",
                    "Planet Traits"
                ]
            }
        }
    },
    "Hyla": {
        "planets": {
            "": {
                "link": "https://game8.co/games/Starfield/archives/426227",
                "resources": [
                    "Flora",
                    "Fauna",
                    "Resources",
                    "Planet Traits"
                ]
            }
        }
    },
    "Ixyll": {
        "planets": {
            "Ixyll I": {
                "link": "https://game8.co/games/Starfield/archives/426859",
                "resources": [
                    "Flora",
                    "Fauna",
                    "Resources",
                    "Planet Traits"
                ]
            },
            "Ixyll III-a": {
                "link": "https://game8.co/games/Starfield/archives/426863",
                "resources": [
                    "Flora",
                    "Fauna",
                    "Resources",
                    "Planet Traits"
                ]
            },
            "Ixyll VI": {
                "link": "https://game8.co/games/Starfield/archives/426869",
                "resources": [
                    "Flora",
                    "Fauna",
                    "Resources",
                    "Planet Traits"
                ]
            },
            "Ixyll VI-d": {
                "link": "https://game8.co/games/Starfield/archives/426889",
                "resources": [
                    "Flora",
                    "Fauna",
                    "Resources",
                    "Planet Traits"
                ]
            },
            "Ixyll VII-b": {
                "link": "https://game8.co/games/Starfield/archives/426894",
                "resources": [
                    "Flora",
                    "Fauna",
                    "Resources",
                    "Planet Traits"
                ]
            },
            "Ixyll VIII-b": {
                "link": "https://game8.co/games/Starfield/archives/426898",
                "resources": [
                    "",
                    "",
                    "",
                    ""
                ]
            },
            "Ixyll IX-c": {
                "link": "https://game8.co/games/Starfield/archives/426903",
                "resources": [
                    "",
                    "",
                    "",
                    ""
                ]
            }
        }
    },
    "Freya": {
        "planets": {
            "": {
                "link": "https://game8.co/games/Starfield/archives/426620",
                "resources": [
                    "",
                    "",
                    "",
                    ""
                ]
            }
        }
    },
    "Rasalhague": {
        "planets": {
            "": {
                "link": "https://game8.co/games/Starfield/archives/428822",
                "resources": [
                    "Flora",
                    "Fauna",
                    "Resources",
                    "Planet Traits"
                ]
            }
        }
    },
    "Nirvana": {
        "planets": {
            "": {
                "link": "https://game8.co/games/Starfield/archives/428908",
                "resources": [
                    "Flora",
                    "Fauna",
                    "Resources",
                    "Planet Traits"
                ]
            }
        }
    },
    "Moloch": {
        "planets": {
            "": {
                "link": "https://game8.co/games/Starfield/archives/428937",
                "resources": [
                    "Flora",
                    "Fauna",
                    "Resources",
                    "Planet Traits"
                ]
            }
        }
    },
    "Khayyam": {
        "planets": {
            "": {
                "link": "https://game8.co/games/Starfield/archives/428987",
                "resources": [
                    "Flora",
                    "Fauna",
                    "Resources",
                    "Planet Traits"
                ]
            }
        }
    },
    "Beta Ternion": {
        "planets": {
            "": {
                "link": "https://game8.co/games/Starfield/archives/428945",
                "resources": [
                    "",
                    "",
                    "",
                    ""
                ]
            }
        }
    },
    "Bara": {
        "planets": {
            "": {
                "link": "https://game8.co/games/Starfield/archives/429137",
                "resources": [
                    "Flora",
                    "Fauna",
                    "Resources",
                    "Planet Traits"
                ]
            }
        }
    },
    "Alpha Marae": {
        "planets": {
            "": {
                "link": "https://game8.co/games/Starfield/archives/427665",
                "resources": [
                    "Flora",
                    "Fauna",
                    "Resources",
                    "Planet Traits"
                ]
            }
        }
    },
    "Beta Marae": {
        "planets": {
            "": {
                "link": "https://game8.co/games/Starfield/archives/429163",
                "resources": [
                    "Flora",
                    "Fauna",
                    "Resources",
                    "Planet Traits"
                ]
            }
        }
    },
    "Tidacha": {
        "planets": {
            "": {
                "link": "https://game8.co/games/Starfield/archives/427044",
                "resources": [
                    "Flora",
                    "Fauna",
                    "Resources",
                    "Planet Traits"
                ]
            }
        }
    },
    "Ophion": {
        "planets": {
            "": {
                "link": "https://game8.co/games/Starfield/archives/428950",
                "resources": [
                    "Flora",
                    "Fauna",
                    "Resources",
                    "Planet Traits"
                ]
            }
        }
    },
    "Heinlein": {
        "planets": {
            "Heinlein I": {
                "link": "https://game8.co/games/Starfield/archives/428996",
                "resources": [
                    "Flora",
                    "Fauna",
                    "Resources",
                    "Planet Traits"
                ]
            },
            "Heinlein III": {
                "link": "https://game8.co/games/Starfield/archives/429000",
                "resources": [
                    "Flora",
                    "Fauna",
                    "Resources",
                    "Planet Traits"
                ]
            },
            "Heinlein IV-b": {
                "link": "https://game8.co/games/Starfield/archives/429005",
                "resources": [
                    "Flora",
                    "Fauna",
                    "Resources",
                    "Planet Traits"
                ]
            },
            "Heinlein V": {
                "link": "https://game8.co/games/Starfield/archives/429012",
                "resources": [
                    "Flora",
                    "Fauna",
                    "Resources",
                    "Planet Traits"
                ]
            },
            "Heinlein VI": {
                "link": "https://game8.co/games/Starfield/archives/429028",
                "resources": [
                    "",
                    "",
                    "",
                    ""
                ]
            },
            "Heinlein VI-d": {
                "link": "https://game8.co/games/Starfield/archives/429041",
                "resources": [
                    "Flora",
                    "Fauna",
                    "Resources",
                    "Planet Traits"
                ]
            }
        }
    },
    "Rutherford": {
        "planets": {
            "": {
                "link": "https://game8.co/games/Starfield/archives/429124",
                "resources": [
                    "Flora",
                    "Fauna",
                    "Resources",
                    "Planet Traits"
                ]
            }
        }
    },
    "Linnaeus": {
        "planets": {
            "": {
                "link": "https://game8.co/games/Starfield/archives/426266",
                "resources": [
                    "Flora",
                    "Fauna",
                    "Resources",
                    "Planet Traits"
                ]
            }
        }
    },
    "Delta Vulpes": {
        "planets": {
            "": {
                "link": "https://game8.co/games/Starfield/archives/426820",
                "resources": [
                    "Flora",
                    "Fauna",
                    "Resources",
                    "Planet Traits"
                ]
            }
        }
    },
    "Gamma Vulpes": {
        "planets": {
            "": {
                "link": "https://game8.co/games/Starfield/archives/426415",
                "resources": [
                    "Flora",
                    "Fauna",
                    "Resources",
                    "Planet Traits"
                ]
            }
        }
    },
    "Xi Ophiuchi": {
        "planets": {
            "": {
                "link": "https://game8.co/games/Starfield/archives/429207",
                "resources": [
                    "Flora",
                    "Fauna",
                    "Resources",
                    "Planet Traits"
                ]
            }
        }
    },
    "Zeta Ophiuchi": {
        "planets": {
            "": {
                "link": "https://game8.co/games/Starfield/archives/426081",
                "resources": [
                    "Flora",
                    "Fauna",
                    "Resources",
                    "Planet Traits"
                ]
            }
        }
    },
    "Bannoc": {
        "planets": {
            "Bannoc I": {
                "link": "https://game8.co/games/Starfield/archives/429170",
                "resources": [
                    "Flora",
                    "Fauna",
                    "Resources",
                    "Planet Traits"
                ]
            },
            "Bannoc IV": {
                "link": "https://game8.co/games/Starfield/archives/429169",
                "resources": [
                    "",
                    "",
                    "",
                    ""
                ]
            }
        }
    },
    "Zosma": {
        "planets": {
            "": {
                "link": "https://game8.co/games/Starfield/archives/429046",
                "resources": [
                    "Flora",
                    "Fauna",
                    "Resources",
                    "Planet Traits"
                ]
            }
        }
    },
    "Bannoc Secondus": {
        "planets": {
            "": {
                "link": "https://game8.co/games/Starfield/archives/429180",
                "resources": [
                    "Flora",
                    "Fauna",
                    "Resources",
                    "Planet Traits"
                ]
            }
        }
    },
    "Alchiba": {
        "planets": {
            "": {
                "link": "https://game8.co/games/Starfield/archives/429289",
                "resources": [
                    "Flora",
                    "Fauna",
                    "Resources",
                    "Planet Traits"
                ]
            }
        }
    },
    "Serpentis": {
        "planets": {
            "": {
                "link": "https://game8.co/games/Starfield/archives/427166",
                "resources": [
                    "Flora",
                    "Fauna",
                    "Resources",
                    "Planet Traits"
                ]
            }
        }
    },
    "Heisenberg": {
        "planets": {
            "": {
                "link": "https://game8.co/games/Starfield/archives/427250",
                "resources": [
                    "Flora",
                    "Fauna",
                    "Resources",
                    "Planet Traits"
                ]
            }
        }
    },
    "Feynman": {
        "planets": {
            "": {
                "link": "https://game8.co/games/Starfield/archives/426246",
                "resources": [
                    "Flora",
                    "Fauna",
                    "Resources",
                    "Planet Traits"
                ]
            }
        }
    },
    "Newton": {
        "planets": {
            "Newton I": {
                "link": "https://game8.co/games/Starfield/archives/425927",
                "resources": [
                    "Flora",
                    "Fauna",
                    "Resources",
                    "Planet Traits"
                ]
            },
            "Newton II-b": {
                "link": "https://game8.co/games/Starfield/archives/425930",
                "resources": [
                    "Flora",
                    "Fauna",
                    "Resources",
                    "Planet Traits"
                ]
            },
            "Newton V-a": {
                "link": "https://game8.co/games/Starfield/archives/425934",
                "resources": [
                    "Flora",
                    "Fauna",
                    "Resources",
                    "Planet Traits"
                ]
            }
        }
    },
    "Leviathan": {
        "planets": {
            "": {
                "link": "https://game8.co/games/Starfield/archives/426429",
                "resources": [
                    "",
                    "",
                    "",
                    ""
                ]
            }
        }
    },
    "Bel": {
        "planets": {
            "Bel I": {
                "link": "https://game8.co/games/Starfield/archives/429214",
                "resources": [
                    "Flora",
                    "Fauna",
                    "Resources",
                    "Planet Traits"
                ]
            },
            "Bel III": {
                "link": "https://game8.co/games/Starfield/archives/429218",
                "resources": [
                    "Flora",
                    "Fauna",
                    "Resources",
                    "Planet Traits"
                ]
            },
            "Bel IV": {
                "link": "https://game8.co/games/Starfield/archives/429222",
                "resources": [
                    "Flora",
                    "Fauna",
                    "Resources",
                    "Planet Traits"
                ]
            },
            "Bel IV-c": {
                "link": "https://game8.co/games/Starfield/archives/429226",
                "resources": [
                    "Flora",
                    "Fauna",
                    "Resources",
                    "Planet Traits"
                ]
            },
            "Bel VI": {
                "link": "https://game8.co/games/Starfield/archives/429231",
                "resources": [
                    "Flora",
                    "Fauna",
                    "Resources",
                    "Planet Traits"
                ]
            }
        }
    },
    "Syrma": {
        "planets": {
            "": {
                "link": "https://game8.co/games/Starfield/archives/427286",
                "resources": [
                    "Flora",
                    "Fauna",
                    "Resources",
                    "Planet Traits"
                ]
            }
        }
    },
    "Nirah": {
        "planets": {
            "": {
                "link": "https://game8.co/games/Starfield/archives/428026",
                "resources": [
                    "Flora",
                    "Fauna",
                    "Resources",
                    "Planet Traits"
                ]
            }
        }
    },
    "Foucault": {
        "planets": {
            "": {
                "link": "https://game8.co/games/Starfield/archives/429359",
                "resources": [
                    "Flora",
                    "Fauna",
                    "Resources",
                    "Planet Traits"
                ]
            }
        }
    },
    "Maal": {
        "planets": {
            "": {
                "link": "https://game8.co/games/Starfield/archives/427290",
                "resources": [
                    "Flora",
                    "Fauna",
                    "Resources",
                    "Planet Traits"
                ]
            }
        }
    },
    "Decaran": {
        "planets": {
            "": {
                "link": "https://game8.co/games/Starfield/archives/427013",
                "resources": [
                    "Flora",
                    "Fauna",
                    "Resources",
                    "Planet Traits"
                ]
            }
        }
    },
    "Alpha Ternion": {
        "planets": {
            "": {
                "link": "https://game8.co/games/Starfield/archives/427868",
                "resources": [
                    "Flora",
                    "Fauna",
                    "Resources",
                    "Planet Traits"
                ]
            }
        }
    }
}